pyppeteers/__init__.py
pyppeteers-0.1.dist-info/WHEEL
pyppeteers-0.1.dist-info/METADATA
pyppeteers-0.1.dist-info/RECORD
