Metadata-Version: 2.1
Name: pyppeteers
Version: 0.1
Summary: pyppeteers
Keywords: 
